staging/__init__.py
staging/config.py
staging/executable.py
staging/logger.py
staging/parallel.py
staging/stage.py
staging/step.py
staging-0.0.3.dist-info/LICENSE
staging-0.0.3.dist-info/METADATA
staging-0.0.3.dist-info/WHEEL
staging-0.0.3.dist-info/entry_points.txt
staging-0.0.3.dist-info/top_level.txt
staging-0.0.3.dist-info/RECORD
