Metadata-Version: 2.2
Name: staging
Version: 0.0.3
Summary: Execute pipeline stages and steps
Author-email: Radoslaw Gryta <radek.gryta@gmail.com>
Project-URL: Homepage, https://github.com/rgryta/Staging
Project-URL: Bug Tracker, https://github.com/rgryta/Staging/issues
Keywords: CI,CD,stage,step,pipeline,workflow,automation,orchestration,execution,staging
Classifier: Programming Language :: Python :: 3
Classifier: License :: OSI Approved :: MIT License
Classifier: Operating System :: OS Independent
Requires-Python: >=3.11
License-File: LICENSE
Requires-Dist: tomlkit
Requires-Dist: dataclass-wizard
Requires-Dist: tzdata
Provides-Extra: dev
Requires-Dist: staging; extra == "dev"
Requires-Dist: black; extra == "dev"
Requires-Dist: isort; extra == "dev"
Requires-Dist: noprint; extra == "dev"
Requires-Dist: pylint; extra == "dev"
Requires-Dist: bump-my-version; extra == "dev"
Requires-Dist: mock; extra == "dev"
Requires-Dist: pytest; extra == "dev"
Requires-Dist: pytest-sugar; extra == "dev"
Requires-Dist: pytest-xdist; extra == "dev"
Requires-Dist: pytest-asyncio; extra == "dev"
Requires-Dist: pytest-timeout; extra == "dev"
Requires-Dist: coverage[toml]; extra == "dev"
